av2-0.3.5.dist-info/METADATA
av2-0.3.5.dist-info/WHEEL
av2-0.3.5.dist-info/licenses/LICENSE
av2-0.3.5.dist-info/licenses/NOTICE
av2/__init__.py
av2/_r.cpython-39-darwin.so
av2/_r.pyi
av2/datasets/__init__.py
av2/datasets/lidar/__init__.py
av2/datasets/lidar/splits.py
av2/datasets/motion_forecasting/__init__.py
av2/datasets/motion_forecasting/constants.py
av2/datasets/motion_forecasting/data_schema.py
av2/datasets/motion_forecasting/eval/__init__.py
av2/datasets/motion_forecasting/eval/metrics.py
av2/datasets/motion_forecasting/eval/submission.py
av2/datasets/motion_forecasting/scenario_serialization.py
av2/datasets/motion_forecasting/viz/__init__.py
av2/datasets/motion_forecasting/viz/scenario_visualization.py
av2/datasets/sensor/__init__.py
av2/datasets/sensor/av2_sensor_dataloader.py
av2/datasets/sensor/constants.py
av2/datasets/sensor/sensor_dataloader.py
av2/datasets/sensor/splits.py
av2/datasets/sensor/utils.py
av2/datasets/tbv/scene_clusters.py
av2/datasets/tbv/splits.py
av2/evaluation/__init__.py
av2/evaluation/detection/__init__.py
av2/evaluation/detection/constants.py
av2/evaluation/detection/eval.py
av2/evaluation/detection/utils.py
av2/evaluation/forecasting/__init__.py
av2/evaluation/forecasting/constants.py
av2/evaluation/forecasting/eval.py
av2/evaluation/forecasting/utils.py
av2/evaluation/scenario_mining/__init__.py
av2/evaluation/scenario_mining/eval.py
av2/evaluation/scene_flow/constants.py
av2/evaluation/scene_flow/eval.py
av2/evaluation/scene_flow/example_submission.py
av2/evaluation/scene_flow/make_annotation_files.py
av2/evaluation/scene_flow/make_mask_files.py
av2/evaluation/scene_flow/make_submission_archive.py
av2/evaluation/scene_flow/utils.py
av2/evaluation/tracking/__init__.py
av2/evaluation/tracking/constants.py
av2/evaluation/tracking/eval.py
av2/evaluation/tracking/utils.py
av2/evaluation/typing.py
av2/geometry/__init__.py
av2/geometry/camera/__init__.py
av2/geometry/camera/pinhole_camera.py
av2/geometry/geometry.py
av2/geometry/infinity_norm_utils.py
av2/geometry/interpolate.py
av2/geometry/iou.py
av2/geometry/mesh_grid.py
av2/geometry/polyline_utils.py
av2-0.3.5.dist-info/RECORD
