Metadata-Version: 2.4
Name: av2
Version: 0.3.5
Classifier: License :: OSI Approved :: MIT License
Classifier: Operating System :: OS Independent
Classifier: Programming Language :: Python
Classifier: Programming Language :: Python :: 3.9
Classifier: Programming Language :: Python :: 3.10
Classifier: Programming Language :: Python :: 3.11
Classifier: Programming Language :: Python :: 3.12
Classifier: Programming Language :: Python :: 3 :: Only
Classifier: Programming Language :: Rust
Requires-Dist: av
Requires-Dist: click
Requires-Dist: joblib
Requires-Dist: kornia
Requires-Dist: matplotlib
Requires-Dist: nox
Requires-Dist: numba
Requires-Dist: numpy
Requires-Dist: opencv-python
Requires-Dist: pandas
Requires-Dist: polars
Requires-Dist: pyarrow
Requires-Dist: pyproj
Requires-Dist: rich
Requires-Dist: scipy
Requires-Dist: torch
Requires-Dist: tqdm
Requires-Dist: universal-pathlib
Requires-Dist: black[jupyter] ; extra == 'lint'
Requires-Dist: mypy ; extra == 'lint'
Requires-Dist: ruff ; extra == 'lint'
Requires-Dist: pytest ; extra == 'test'
Requires-Dist: pytest-benchmark ; extra == 'test'
Requires-Dist: pytest-cov ; extra == 'test'
Provides-Extra: lint
Provides-Extra: test
License-File: LICENSE
License-File: NOTICE
Summary: Argoverse 2: Next generation datasets for self-driving perception and forecasting.
Keywords: argoverse,argoverse2,autonomous-driving,av1,av2,3d-object-detection,3d-scene-flow,4d-occupancy-forecasting,e2e-forecasting,motion-forecasting
Home-Page: https://github.com/argoverse/av2-api
Requires-Python: >=3.8
Project-URL: homepage, https://argoverse.org
Project-URL: repository, https://github.com/argoverse/av2-api
